Workbook

Sheet Read Me
A1: Slide 9 — Unit Economics & 30–60–90 | Calculation Workbook
A3: Purpose | B3: Explains every calculation used on Slide 9 in a clean, formula-driven model.
A4: Core economic hurdle | B4: ₹120 incremental reverse logistics cost per RTO (DICE case-pack assumption).
A5: Core equation | B5: Expected Net Value = P(save) × ₹120 − Intervention Cost.
A6: Break-even rule | B6: P(save) > Intervention Cost ÷ ₹120.
A7: Primary scale metric | B7: Cost per RTO avoided = Incremental intervention spend ÷ Incremental RTOs avoided.
A8: Scale gate | B8: Scale only where Cost / RTO avoided < ₹120 and rider, CX, SLA and operational guardrails hold.
A10: Workbook conventions
A11: Blue font | B11: Hardcoded assumptions / scenario inputs
A12: Black font | B12: Formulas / calculations
A13: Green font | B13: Links from another worksheet
A14: Yellow fill | B14: Key assumption / cell to review
A15: Source basis | B15: Slide 9 analysis + uploaded revised solution architecture + DICE case-pack assumptions

Sheet Core Inputs
A1: Core Inputs & Scenario Assumptions
A3: DICE case-pack economics
A4: Input | B4: Value | C4: Unit / note
A5: Forward logistics cost | B5: 50 | C5: ₹ / shipped order
A6: Incremental reverse logistics cost | B6: 120 | C6: ₹ / RTO order
A7: Current blended RTO rate | B7: 0.17 | C7: % of shipped orders; DICE case-pack
A8: Total logistics cost of a failed order | B8: =B5+B6 -> 170 | C8: ₹ / RTO order = forward + reverse
A9: Zero-RTO cost per successful delivery | B9: 50 | C9: ₹ / successful delivery
A10: Actual cost per successful delivery at 17% RTO | B10: =(100*B5+100*B7*B6)/(100*(1-B7)) -> 84.819277 | C10: ₹ / successful delivery
A11: RTO-driven cost uplift vs zero RTO | B11: =B10/B9-1 -> 0.69638554 | C11: %
A13: Illustrative intervention costs for pilot testing
A14: Intervention | B14: Cost / action (₹) | C14: Use
A15: WhatsApp / SMS | B15: 2 | C15: Low-cost outreach
A16: Automated AI call | B16: 5 | C16: IVR / automated call
A17: Assisted human call | B17: 10 | C17: Higher-touch recovery
A18: Kirana recovery handling | B18: 15 | C18: Illustrative handling assumption
A19: Rider reattempt | B19: 20 | C19: Difficulty-based reattempt cost
A20: Reroute to nearby hub | B20: 30 | C20: Selective network correction
A22: Worked-example inputs
A23: Input | B23: Value | C23: Unit
A24: First-NDR orders | B24: 10000 | C24: orders
A25: Intervention cost per order | B25: 5 | C25: ₹ / order
A26: RTOs avoided | B26: 600 | C26: orders
A27: Assumed save rate | B27: =B26/B24 -> 0.06 | C27: % of first-NDR orders
A28: Intervention spend | B28: =B24*B25 -> 50000 | C28: ₹
A30: Other scenario inputs
A31: Input | B31: Value | C31: Unit / note
A32: Rider save probability (example) | B32: 0.3 | C32: 30% example
A33: Kirana handling cost | B33: 15 | C33: ₹ / recovered parcel
A34: Kirana eligible parcels | B34: 1000 | C34: parcels
A35: Recovery rates tested | B35: 5%, 10%, 12.5%, 20%, 30%, 40% | C35: scenario range

Sheet Intervention Econ
A1: Intervention Economics — Break-Even Hurdles
A3: Formula: Break-even save probability = Intervention cost ÷ ₹120
A4: Intervention | B4: Cost / action (₹) | C4: Break-even P(save) | D4: Expected value if save P = 10% | E4: Expected net value at 10% | F4: Comment
A5: WhatsApp / SMS | B5: ='Core Inputs'!B15 -> 2 | C5: =B5/'Core Inputs'!$B$8 -> 0.011764706 | D5: =0.1*'Core Inputs'!$B$8 -> 17 | E5: =D5-B5 -> 15 | F5: Low-cost pre-dispatch prevention
A6: Automated AI call | B6: ='Core Inputs'!B16 -> 5 | C6: =B6/'Core Inputs'!$B$8 -> 0.029411765 | D6: =0.1*'Core Inputs'!$B$8 -> 17 | E6: =D6-B6 -> 12 | F6: Moderate-cost intent confirmation
A7: Assisted human call | B7: ='Core Inputs'!B17 -> 10 | C7: =B7/'Core Inputs'!$B$8 -> 0.058823529 | D7: =0.1*'Core Inputs'!$B$8 -> 17 | E7: =D7-B7 -> 7 | F7: Higher-touch pre-dispatch recovery
A8: Kirana recovery handling | B8: ='Core Inputs'!B18 -> 15 | C8: =B8/'Core Inputs'!$B$6 -> 0.125 | D8: =0.1*'Core Inputs'!$B$6 -> 12 | E8: =D8-B8 -> -3 | F8: Positive if recovery rate clears threshold
A9: Rider reattempt | B9: ='Core Inputs'!B19 -> 20 | C9: =B9/'Core Inputs'!$B$6 -> 0.16666667 | D9: =0.1*'Core Inputs'!$B$6 -> 12 | E9: =D9-B9 -> -8 | F9: Needs meaningful conversion uplift
A10: Reroute to nearby hub | B10: ='Core Inputs'!B20 -> 30 | C10: =B10/'Core Inputs'!$B$6 -> 0.25 | D10: =0.1*'Core Inputs'!$B$6 -> 12 | E10: =D10-B10 -> -18 | F10: Use selectively
A12: Cost per RTO avoided
A13: Metric | B13: Formula | C13: Illustrative input | D13: Result | E13: Decision
A14: Intervention spend | B14: Orders × cost/order | C14: ='Core Inputs'!B28 -> 50000 | D14: =C14 -> 50000
A15: RTOs avoided | B15: Observed incremental difference vs control | C15: 600
A16: Cost / RTO avoided | B16: Spend ÷ RTOs avoided | C16: =D14/C15 -> 83.333333 | D16: =C16 -> 83.333333
A17: Net value | B17: RTOs avoided × ₹120 − spend | C17: =C15*'Core Inputs'!B6-C14 -> 22000 | D17: =C17 -> 22000

Sheet Worked Example
A1: Worked Example — Assisted Contact Pilot
A3: Illustrative scenario from Slide 9 | D3: Math
A4: Input | B4: Value | D4: Metric | E4: Formula | F4: Result | G4: Interpretation
A5: First-NDR orders | B5: ='Core Inputs'!B24 -> 10000 | D5: Intervention spend | E5: 10,000 × ₹5 | F5: =B7 -> 50000 | G5: Cash cost of pilot
A6: Intervention cost / order | B6: ='Core Inputs'!B25 -> 5 | D6: Reverse cost avoided | E6: 600 × ₹120 | F6: =B8*'Core Inputs'!B6 -> 72000 | G6: Value unlocked
A7: Intervention spend | B7: ='Core Inputs'!B28 -> 50000 | D7: Net reverse-cost value | E7: ₹72,000 − ₹50,000 | F7: =F6-F5 -> 22000 | G7: Value after intervention spend
A8: RTOs avoided | B8: ='Core Inputs'!B26 -> 600 | D8: Cost / RTO avoided | E8: ₹50,000 ÷ 600 | F8: =F5/B8 -> 83.333333 | G8: Compare with ₹120 hurdle
A9: Save rate | B9: =B8/B5 -> 0.06 | D9: Economic test | E9: ₹83.3 < ₹120 | F9: =IF(F8<'Core Inputs'!B6,"PASS","FAIL") -> PASS | G9: Pass

Sheet Sensitivity
A1: Sensitivity — Intervention Spend vs RTO Save Rate
A3: Base case: 10,000 first-NDR orders; ₹5 intervention cost / order
A4: RTO save rate | B4: RTOs avoided | C4: Value saved @ ₹120 | D4: Intervention cost | E4: Net value | F4: Cost / RTO avoided
A5: 0.02 | B5: =A5*'Core Inputs'!$B$24 -> 200 | C5: =B5*'Core Inputs'!$B$6 -> 24000 | D5: ='Core Inputs'!$B$28 -> 50000 | E5: =C5-D5 -> -26000 | F5: =D5/B5 -> 250
A6: 0.05 | B6: =A6*'Core Inputs'!$B$24 -> 500 | C6: =B6*'Core Inputs'!$B$6 -> 60000 | D6: ='Core Inputs'!$B$28 -> 50000 | E6: =C6-D6 -> 10000 | F6: =D6/B6 -> 100
A7: 0.1 | B7: =A7*'Core Inputs'!$B$24 -> 1000 | C7: =B7*'Core Inputs'!$B$6 -> 120000 | D7: ='Core Inputs'!$B$28 -> 50000 | E7: =C7-D7 -> 70000 | F7: =D7/B7 -> 50
A8: 0.15 | B8: =A8*'Core Inputs'!$B$24 -> 1500 | C8: =B8*'Core Inputs'!$B$6 -> 180000 | D8: ='Core Inputs'!$B$28 -> 50000 | E8: =C8-D8 -> 130000 | F8: =D8/B8 -> 33.333333
A9: 0.2 | B9: =A9*'Core Inputs'!$B$24 -> 2000 | C9: =B9*'Core Inputs'!$B$6 -> 240000 | D9: ='Core Inputs'!$B$28 -> 50000 | E9: =C9-D9 -> 190000 | F9: =D9/B9 -> 25
A11: Break-even check
A12: Metric | B12: Formula | C12: Result
A13: Break-even save probability | B13: ₹5 ÷ ₹120 | C13: ='Core Inputs'!B25/'Core Inputs'!B6 -> 0.041666667
A14: Minimum whole-order example | B14: At 10,000 orders | C14: =C13*'Core Inputs'!B24 -> 416.66667
A15: Rule | B15: Save rate > break-even | C15: =IF(A6>C13,"PASS","FAIL") -> PASS

Sheet Rider Economics
A1: Rider Economics — Difficulty-Adjusted Premium
A3: Rule: Maximum economically justified premium = P(save) × ₹120
A4: Save probability | B4: RTO value at stake | C4: Max premium ceiling | D4: Example premium | E4: Headroom vs example
A5: 0.1 | B5: =A5*'Core Inputs'!$B$6 -> 12 | C5: =B5 -> 12 | D5: 20 | E5: =C5-D5 -> -8
A6: 0.2 | B6: =A6*'Core Inputs'!$B$6 -> 24 | C6: =B6 -> 24 | D6: 20 | E6: =C6-D6 -> 4
A7: 0.3 | B7: =A7*'Core Inputs'!$B$6 -> 36 | C7: =B7 -> 36 | D7: 20 | E7: =C7-D7 -> 16
A8: 0.4 | B8: =A8*'Core Inputs'!$B$6 -> 48 | C8: =B8 -> 48 | D8: 20 | E8: =C8-D8 -> 28
A9: 0.5 | B9: =A9*'Core Inputs'!$B$6 -> 60 | C9: =B9 -> 60 | D9: 20 | E9: =C9-D9 -> 40
A11: Difficulty-adjusted operating logic
A12: Step | B12: Question / calculation | C12: If yes | D12: If no
A13: 1. Allocation | B13: Is the LMDC assignment appropriate? | C13: Continue risk check | D13: Reallocate before incentive
A14: 2. Difficulty | B14: Score distance + address confidence + pincode RTO history + COD / intent | C14: Continue | D14: Normal delivery economics
A15: 3. Threshold | B15: Is difficulty above the premium threshold? | C15: Apply targeted premium | D15: No premium
A16: 4. Verified attempt | B16: GPS + timestamp/dwell + customer contact + reason code | C16: Eligible for failed-attempt compensation | D16: No compensation
A17: 5. Economic cap | B17: Premium < P(save) × ₹120 | C17: Contribution-positive | D17: Reduce / remove premium

Sheet Kirana Economics
A1: Kirana Recovery Economics
A3: Simplified gate: P(recovery) × ₹120 > handling + transfer + kirana payout
A4: Recovery rate | B4: Parcels recovered | C4: Reverse cost avoided | D4: Handling cost @ ₹15 | E4: Net before transfer/payout
A5: 0.05 | B5: =A5*'Core Inputs'!$B$34 -> 50 | C5: =B5*'Core Inputs'!$B$6 -> 6000 | D5: =B5*'Core Inputs'!$B$33 -> 750 | E5: =C5-D5 -> 5250
A6: 0.1 | B6: =A6*'Core Inputs'!$B$34 -> 100 | C6: =B6*'Core Inputs'!$B$6 -> 12000 | D6: =B6*'Core Inputs'!$B$33 -> 1500 | E6: =C6-D6 -> 10500
A7: 0.125 | B7: =A7*'Core Inputs'!$B$34 -> 125 | C7: =B7*'Core Inputs'!$B$6 -> 15000 | D7: =B7*'Core Inputs'!$B$33 -> 1875 | E7: =C7-D7 -> 13125
A8: 0.2 | B8: =A8*'Core Inputs'!$B$34 -> 200 | C8: =B8*'Core Inputs'!$B$6 -> 24000 | D8: =B8*'Core Inputs'!$B$33 -> 3000 | E8: =C8-D8 -> 21000
A9: 0.3 | B9: =A9*'Core Inputs'!$B$34 -> 300 | C9: =B9*'Core Inputs'!$B$6 -> 36000 | D9: =B9*'Core Inputs'!$B$33 -> 4500 | E9: =C9-D9 -> 31500
A10: 0.4 | B10: =A10*'Core Inputs'!$B$34 -> 400 | C10: =B10*'Core Inputs'!$B$6 -> 48000 | D10: =B10*'Core Inputs'!$B$33 -> 6000 | E10: =C10-D10 -> 42000
A11: Break-even | B11: ='Core Inputs'!B33/'Core Inputs'!B6*'Core Inputs'!B34 -> 125 | C11: =B11*'Core Inputs'!B6 -> 15000 | D11: =B11*'Core Inputs'!B33 -> 1875 | E11: =C11-D11 -> 13125
A13: What the calculation means
A14: Step | B14: Formula | C14: Interpretation
A15: Avoided reverse cost | B15: Recovered parcels × ₹120 | C15: Value released by not sending recovered parcels through reverse logistics.
A16: Handling cost | B16: Recovered parcels × ₹15 | C16: Illustrative local handling expense; excludes transfer/payout unless separately modelled.

Sheet Return-to-Value
A1: Return-to-Value — Full Economic Gate
A3: Input a seller-authorized local recovery scenario; formulas calculate net value
A4: Input | B4: Illustrative value | C4: Unit / note
A5: Recovery revenue / new sale | B5: 280 | C5: ₹ / recovered parcel
A6: Seller-approved discount | B6: 65 | C6: ₹ / parcel
A7: Local fulfilment / pickup | B7: 30 | C7: ₹ / parcel
A8: Kirana / handling | B8: 15 | C8: ₹ / parcel
A9: Payment processing | B9: 5 | C9: ₹ / parcel
A10: Expected second-RTO cost | B10: 12 | C10: ₹ / parcel
A11: Reverse logistics avoided | B11: ='Core Inputs'!B6 -> 120 | C11: ₹120 / parcel
A12: Net Recovery Value | B12: =B5-B6-B7-B8-B9-B10+B11 -> 273 | C12: per recovered parcel
A14: Decision rule
A15: Test | B15: Formula | C15: Interpretation
A16: Seller authorization | B16: Yes / No | C16: Must be Yes
A17: Parcel eligibility | B17: Sealed + eligible + local demand | C17: Otherwise return
A18: Economic gate | B18: Expected Recovery Value > normal return economics | C18: Use local recovery only when positive

Sheet Pilot Plan
A1: 30–60–90 Pilot & Scale Gates
A3: Pilot roadmap
A4: Phase | B4: Days | C4: Objective | D4: Core scope | E4: Primary test | F4: Decision
A5: Prove | B5: 0–30 | C5: Validate economic impact | D5: First-NDR, COD-heavy; rule-based Intercept | E5: Control vs treatment | F5: Proceed if economics are positive
A6: Optimise | B6: 31–60 | C6: Improve fit and operations | D6: LMDC fit, difficulty premium, verified attempts, Kirana nodes | E6: Segment by cause / distance / pincode | F6: Retain only winning interventions
A7: Scale | B7: 61–90 | C7: Integrate and expand | D7: Decision engine + routing + rider + recovery | E7: Expand to categories/geographies | F7: Scale only after all gates pass
A8: Day 90 gate | C8: Scale / stop / modify
A10: Scale scorecard
A11: Gate | B11: Scale condition | C11: Metric
A12: Economics | B12: Cost / RTO avoided < ₹120 | C12: ₹ / RTO avoided
A13: RTO impact | B13: Meaningful reduction vs control | C13: RTO % / NDR→delivery
A14: Rider health | B14: Earnings / productive hour not lower | C14: ₹ / productive hour
A15: Customer | B15: No deterioration | C15: Complaint rate / CSAT
A16: Speed | B16: No material TAT / SLA degradation | C16: Delivery TAT
A17: Operations | B17: No material complexity / fraud / damage increase | C17: Operational exception rate
A18: Recovery | B18: Positive recovery economics | C18: Net value / recovered parcel

Sheet Math Guide
A1: Math Guide — What Each Calculation Means
A3: Calculation | B3: Formula | C3: Plain-English meaning | D3: Used on slide | E3: Sheet
A4: Incremental reverse cost | B4: ₹120 | C4: Cost avoided when an RTO is prevented/recovered, based on DICE case-pack. | D4: Post-dispatch hurdle / rescue | E4: Core Inputs
A5: Pre-dispatch net value | B5: P(save) × ₹170 − C(intervention) | C5: Successful prevention avoids ₹50 forward + ₹120 reverse. | D5: Pre-dispatch interventions | E5: Intervention Econ
A6: Post-dispatch net value | B6: P(RTO avoided) × ₹120 − C(intervention) | C6: Successful rescue avoids the incremental reverse logistics cost. | D6: Post-dispatch interventions | E6: Intervention Econ
A7: Break-even save probability | B7: Cost ÷ value at stake | C7: Minimum save probability needed to pay for the intervention; use ₹170 pre-dispatch or ₹120 post-dispatch. | D7: Break-even ladders | E7: Intervention Econ
A8: Rider premium ceiling | B8: P(save) × ₹120 | C8: Maximum premium supported by expected avoided reverse cost. | D8: Rider economics | E8: Rider Economics
A9: Kirana break-even | B9: Handling ÷ ₹120 | C9: Simplified recovery rate needed to cover illustrative ₹15 handling. | D9: Kirana economics | E9: Kirana Economics
A10: Net Recovery Value | B10: Recovery revenue − discount − local fulfilment − handling − payment cost − second-RTO cost + reverse cost avoided | C10: Full seller-authorized local reallocation economics per recovered parcel. | D10: Return-to-Value | E10: Return-to-Value
A11: Scale decision | B11: All gates pass | C11: Do not scale based on RTO reduction alone; check economics, rider, CX, SLA and operational safety. | D11: 30–60–90 | E11: Pilot Plan

Sheet Sources
A1: Source Notes
A3: Source / basis | B3: Used for | C3: Notes | D3: Reference
A4: Uploaded Slide 9 analysis | B4: Core ₹120 hurdle, formulas, illustrative intervention costs, pilot example, sensitivity, 30–60–90 | C4: Model inputs from the supplied analysis; intervention costs are explicitly described as illustrative pilot assumptions. | D4: User-provided analysis
A5: Uploaded Valmo RTO Revised Solution Architecture | B5: Economic gates, rider premium logic, Kirana ₹15 handling assumption, pilot KPIs and guardrails | C5: Architecture says rider premium should be capped by expected avoided RTO cost and Kirana recovery threshold is 12.5% at ₹15 handling. | D5: User-provided DOCX
A6: DICE case-pack economics | B6: ₹50 forward cost, ₹120 reverse cost, ₹170 total failed-order logistics cost | C6: Illustrative case inputs; keep these labelled as case-pack assumptions in the final deck. | D6: User-provided case material
A7: IIM Mumbai reference slide | B7: Layout / modelling inspiration only | C7: Used for structure: unit economics, scenario comparison, assumptions, success metrics; no content copied. | D7: User-provided reference PDF
A8: Model note | B8: Scope | C8: This workbook explains Slide 9 calculations; it does not claim forecasted Valmo savings. | D8: Internal model note

Sheet Slide 9 Dashboard
A1: 9 | UNIT ECONOMICS & PILOT
A2: PROVE THE ECONOMICS BEFORE WE SCALE
A3: Every intervention must beat the ₹120 reverse-cost hurdle while protecting successful-delivery cost, rider earnings, customer experience and delivery speed.
A5: CORE ECONOMIC ANCHORS | E5: PORTFOLIO SCENARIO | I5: WORKED EXAMPLE | M5: FLASH STORE
A6: ₹120 | B6: Incremental reverse cost / RTO | E6: 17.0% | F6: Current blended RTO | I6: ₹83.3 | J6: Cost / RTO avoided | M6: ₹273 | N6: Net recovery value / recovered parcel
A7: ₹170 | B7: Total failed-order logistics cost | E7: 2.74 pp | F7: Illustrative 50% capture of 5.47pp recoverable pool | I7: ₹22,000 | J7: Net value / 10,000 orders | M7: ₹120 | N7: Reverse cost avoided
A9: A. ECONOMIC ENGINE: THREE TYPES OF INTERVENTIONS
A10: Intervention class | B10: Illustrative action | C10: Value at stake | D10: Core formula | E10: Key economic hurdle | F10: Example cost | G10: Break-even save / recovery | H10: Slide role
A11: 1. PRE-DISPATCH PREVENTION | B11: WhatsApp / SMS; AI call; human call | C11: ₹170 / order | D11: P(save) × ₹170 − C | E11: Cost must be justified by failed-order value avoided | F11: ₹2 / ₹5 / ₹10 | G11: 1.2% / 2.9% / 5.9% | H11: Solution 1
A12: 2. POST-DISPATCH RESCUE | B12: Rider reattempt; nearby-hub reroute | C12: ₹120 / RTO | D12: P(RTO avoided) × ₹120 − C | E12: Cost / RTO avoided < ₹120 | F12: ₹20 / ₹30 | G12: 16.7% / 25.0% | H12: Solutions 2 / 3
A13: 3. LOCAL RECOVERY | B13: Seller-authorized Flash Store recovery | C13: ₹120 reverse + recovered value | D13: Avoided reverse + recovered value − recovery cost | E13: Positive net recovery value | F13: See Return-to-Value | G13: Model per recovered parcel | H13: Solution 8
A15: B. INTERVENTION BREAK-EVEN: WHAT MUST HAPPEN FOR ₹1 SPENT TO PAY BACK? | I15: C. WORKED EXAMPLE: ₹5 AI CALL ON 10,000 FIRST-NDR COD ORDERS
A16: Intervention | B16: Cost / action (₹) | C16: Value / successful save (₹) | D16: Break-even P(save) | E16: Net value at 10% save (₹ / order) | F16: 100-order net value @10% | G16: Use | H16: Decision | I16: Metric | J16: Input / formula | K16: Result
A17: WhatsApp / SMS | B17: ='Core Inputs'!B15 -> 2 | C17: =170 -> 170 | D17: =B17/C17 -> 0.011764706 | E17: =0.1*C17-B17 -> 15 | F17: =E17*100 -> 1500 | G17: Pre-dispatch | H17: Positive at 10% | I17: Targeted orders | J17: 10000 | K17: ='Core Inputs'!B24 -> 10000 | L17: orders
A18: Automated AI call | B18: ='Core Inputs'!B16 -> 5 | C18: =170 -> 170 | D18: =B18/C18 -> 0.029411765 | E18: =0.1*C18-B18 -> 12 | F18: =E18*100 -> 1200 | G18: Pre-dispatch | H18: Positive at 10% | I18: Cost / order | J18: 5 | K18: ='Core Inputs'!B25 -> 5 | L18: ₹ / order
A19: Assisted human call | B19: ='Core Inputs'!B17 -> 10 | C19: =170 -> 170 | D19: =B19/C19 -> 0.058823529 | E19: =0.1*C19-B19 -> 7 | F19: =E19*100 -> 700 | G19: Pre-dispatch | H19: Positive at 10% | I19: Assumed RTO save rate | J19: 0.06 | K19: ='Core Inputs'!B27 -> 0.06 | L19: %
A20: Rider reattempt | B20: ='Core Inputs'!B19 -> 20 | C20: =120 -> 120 | D20: =B20/C20 -> 0.16666667 | E20: =0.1*C20-B20 -> -8 | F20: =E20*100 -> -800 | G20: Post-dispatch | H20: Negative at 10%; needs ≥16.7% | I20: RTOs avoided | K20: =K17*K19 -> 600 | L20: orders
A21: Reroute to nearby hub | B21: ='Core Inputs'!B20 -> 30 | C21: =120 -> 120 | D21: =B21/C21 -> 0.25 | E21: =0.1*C21-B21 -> -18 | F21: =E21*100 -> -1800 | G21: Post-dispatch | H21: Negative at 10%; needs ≥25.0% | I21: Intervention spend | K21: =K17*K18 -> 50000 | L21: ₹
A22: Rural Connection Shield | B22: ='Solution 3 Econ'!B7 -> 30 | C22: =120 -> 120 | D22: =B22/C22 -> 0.25 | E22: =0.1*C22-B22 -> -18 | F22: =E22*100 -> -1800 | G22: Selective protection | H22: Calibrate cost + save probability in pilot | I22: Reverse cost avoided | K22: =K20*'Core Inputs'!B6 -> 72000 | L22: ₹
I23: Net value | K23: =K22-K21 -> 22000 | L23: ₹
I24: Cost / RTO avoided | K24: =K21/K20 -> 83.333333 | L24: ₹ / RTO | M24: Compare to ₹120
A26: E. 30–60–90 PILOT: PROVE → OPTIMISE → SCALE | I26: D. SENSITIVITY: 10,000 ORDERS × ₹5 INTERVENTION COST
A27: Phase | B27: Days | C27: Objective | D27: Core scope | E27: Primary test | F27: Decision | G27: Key evidence | H27: Owner | I27: RTO save rate | J27: RTOs avoided | K27: Value saved | L27: Intervention cost | M27: Net value | N27: Cost / RTO avoided
A28: PROVE | B28: 0–30 | C28: Validate economic impact | D28: First-NDR, COD-heavy; rule-based Intercept | E28: Control vs treatment | F28: Proceed if economics are positive | G28: Incremental RTO reduction + cost / RTO avoided | H28: Operations + Data | I28: 0.02 | J28: =I28*10000 -> 200 | K28: =J28*'Core Inputs'!B6 -> 24000 | L28: 50000 | M28: =K28-L28 -> -26000 | N28: =L28/J28 -> 250
A29: OPTIMISE | B29: 31–60 | C29: Improve fit and operations | D29: LMDC fit, difficulty premium, verified attempts, Kirana nodes | E29: Segment by cause / distance / pincode | F29: Retain only winning interventions | G29: Cause-level uplift + rider/CX impact | H29: Operations + Product | I29: 0.05 | J29: =I29*10000 -> 500 | K29: =J29*'Core Inputs'!B6 -> 60000 | L29: 50000 | M29: =K29-L29 -> 10000 | N29: =L29/J29 -> 100
A30: SCALE | B30: 61–90 | C30: Integrate and expand | D30: Decision engine + routing + rider + recovery | E30: Expand categories / geographies | F30: Scale only after all gates pass | G30: Stable economics + operational health | H30: Product + Operations | I30: 0.1 | J30: =I30*10000 -> 1000 | K30: =J30*'Core Inputs'!B6 -> 120000 | L30: 50000 | M30: =K30-L30 -> 70000 | N30: =L30/J30 -> 50
I31: 0.15 | J31: =I31*10000 -> 1500 | K31: =J31*'Core Inputs'!B6 -> 180000 | L31: 50000 | M31: =K31-L31 -> 130000 | N31: =L31/J31 -> 33.333333
A32: F. SCALE GATE: ALL CONDITIONS MUST HOLD | I32: 0.2 | J32: =I32*10000 -> 2000 | K32: =J32*'Core Inputs'!B6 -> 240000 | L32: 50000 | M32: =K32-L32 -> 190000 | N32: =L32/J32 -> 25
A33: Gate | B33: Scale condition | C33: Metric | D33: Why it matters | E33: Target | F33: Test owner
A34: Economics | B34: Cost / RTO avoided < ₹120 | C34: ₹ / RTO avoided | D34: Value must exceed intervention spend | E34: < ₹120 | F34: Finance / Data
A35: RTO impact | B35: Meaningful reduction vs control | C35: RTO %; NDR → delivery | D35: Measure incremental causal impact | E35: Positive vs control | F35: Data Science | I35: G. RICE PRIORITISATION
A36: Rider health | B36: Earnings / productive hour not lower | C36: ₹ / productive hour | D36: Avoid shifting value from platform to rider | E36: No worse than control | F36: Operations | I36: Formula | J36: Reach × Impact × Confidence ÷ Effort
A37: Customer | B37: No deterioration | C37: Complaint rate / CSAT | D37: Protect customer experience | E37: No material worse | F37: CX | I37: Intervention | J37: Reach | K37: Impact | L37: Confidence | M37: Effort | N37: RICE
A38: Speed | B38: No material TAT / SLA degradation | C38: Delivery TAT | D38: Do not buy RTO improvement by slowing service | E38: No material worse | F38: Operations | I38: Assisted contact / confirmation | N38: =IFERROR(J38*K38*L38/M38,0) -> 0
A39: Operations / Risk | B39: No material complexity, fraud or damage increase | C39: Exception rate | D39: Prevent process leakage / abuse | E39: No material increase | F39: Ops Risk | I39: Reschedule / appointment endpoint | N39: =IFERROR(J39*K39*L39/M39,0) -> 0
I40: Rider incentive, difficulty-adjusted | N40: =IFERROR(J40*K40*L40/M40,0) -> 0
A41: KEY TAKEAWAY: RTO REDUCTION IS NOT ENOUGH. SCALE ONLY WHEN INCREMENTAL VALUE EXCEEDS INTERVENTION COST AND ALL CUSTOMER, RIDER, SPEED AND RISK GATES HOLD. | I41: Rural Connection Shield | N41: =IFERROR(J41*K41*L41/M41,0) -> 0
I42: Kirana / Flash Store recovery | N42: =IFERROR(J42*K42*L42/M42,0) -> 0

Sheet Solution 3 Econ
A1: SOLUTION 3 | RURAL CONNECTION SHIELD | ECONOMIC MODEL
A2: Use the existing Valmo route and allocation decision; price the time cost of missing the next rural connection.
A4: Scenario inputs | F4: Decision economics
A5: Input | B5: Value | C5: Unit | D5: Note | F5: Metric | G5: Formula / result | H5: Interpretation
A6: Reverse logistics cost | B6: ='Core Inputs'!B6 -> 120 | C6: ₹ / RTO | D6: Case-pack anchor | F6: Expected value saved / order | G6: =B8*B6 -> 36 | H6: P(save) × ₹120
A7: Protection cost / order | B7: 30 | C7: ₹ / protected order | D7: Scenario input to calibrate in pilot | F7: Expected net value / order | G7: =G6-B7 -> 6 | H7: Value saved − protection cost
A8: Save probability | B8: 0.3 | C8: % of at-risk orders | D8: Scenario input | F8: Break-even save rate | G8: =B7/B6 -> 0.25 | H8: Protection cost ÷ ₹120
A9: Portfolio orders | B9: 10000 | C9: orders | D9: Scenario scale for sensitivity | F9: Net value on scenario orders | G9: =G7*B9 -> 60000 | H9: Net / order × orders
F10: Economic test | G10: =IF(G7>0,"PASS","FAIL") -> PASS | H10: Positive expected net value
A12: Protection-cost sensitivity | F12: Operational KPI linkage
A13: Protection cost / order (₹) | B13: Break-even save rate | C13: Save rate 20% | D13: Net / order @20% | E13: Decision | F13: Metric | G13: What to monitor | H13: Scale implication
A14: 10 | B14: =A14/$B$6 -> 0.083333333 | C14: =$B$6*20% -> 24 | D14: =C14-A14 -> 14 | E14: =IF(D14>0,"Positive","Negative") -> Positive | F14: P90 / P95 rural delivery time | G14: Tail delivery time | H14: Should improve or stay controlled
A15: 20 | B15: =A15/$B$6 -> 0.16666667 | C15: =$B$6*20% -> 24 | D15: =C15-A15 -> 4 | E15: =IF(D15>0,"Positive","Negative") -> Positive | F15: Critical connection miss rate | G15: Missed high-criticality movements | H15: Should decline
A16: 30 | B16: =A16/$B$6 -> 0.25 | C16: =$B$6*20% -> 24 | D16: =C16-A16 -> -6 | E16: =IF(D16>0,"Positive","Negative") -> Negative | F16: Hours added by connection loss | G16: Delay caused by missed connection | H16: Should decline
A17: 40 | B17: =A17/$B$6 -> 0.33333333 | C17: =$B$6*20% -> 24 | D17: =C17-A17 -> -16 | E17: =IF(D17>0,"Positive","Negative") -> Negative | F17: Delayed rural refusal / RTO | G17: Outcome after connection loss | H17: Should decline
A18: 50 | B18: =A18/$B$6 -> 0.41666667 | C18: =$B$6*20% -> 24 | D18: =C18-A18 -> -26 | E18: =IF(D18>0,"Positive","Negative") -> Negative | F18: Incremental cost / hour saved | G18: Economic efficiency | H18: Must justify protection spend
A19: 60 | B19: =A19/$B$6 -> 0.5 | C19: =$B$6*20% -> 24 | D19: =C19-A19 -> -36 | E19: =IF(D19>0,"Positive","Negative") -> Negative

Sheet Solution 4 Econ
A1: SOLUTION 4 | PARTNER PERFORMANCE SCORECARD | ECONOMIC MODEL
A2: Partner-level accountability: difficulty-adjusted execution quality determines coaching, allocation and incentives.
A4: Illustrative recovery economics per 100 orders
A5: Metric | B5: Base | C5: Formula | D5: Result | E5: Unit | F5: 50% capture case | G5: Formula | H5: Result
A6: RTO recovered / 100 orders | B6: 1.04 | C6: Source scenario | D6: 1.04 | E6: orders | G6: 1.04 × 50% | H6: =D6*50% -> 0.52
A7: Reverse cost avoided / 100 | C7: 1.04 × ₹120 | D7: =D6*'Core Inputs'!B6 -> 124.8 | E7: ₹ | G7: 0.52 × ₹120 | H7: =H6*'Core Inputs'!B6 -> 62.4
A8: Operating cost / 100 orders | B8: 35 | C8: Source scenario | D8: =B8 -> 35 | E8: ₹ | F8: 35 | G8: Held constant | H8: =B8 -> 35
A9: Net value / 100 orders | C9: Value avoided − op cost | D9: =D7-D8 -> 89.8 | E9: ₹ | G9: Value avoided − op cost | H9: =H7-H8 -> 27.4
A10: RTO reduction at 50% capture | C10: 1.04 × 50% | D10: =D6*50% -> 0.52 | E10: pp | H10: =D10 -> 0.52
A11: Avoided savings bonus share | B11: 0.25 | C11: Elite partner bonus share | D11: 0.25 | E11: % of savings
A12: Illustrative partner volume | B12: 2000 | C12: orders | D12: 2000 | E12: orders
A14: Illustrative 2,000-delivery partner example
A15: Metric | B15: Formula | C15: Result | D15: Unit | E15: Interpretation
A16: RTO reduction | B16: 3.0% × 2,000 | C16: =3%*2000 -> 60 | D16: orders avoided | E16: 60 RTOs avoided
A17: Reverse cost saved | B17: 60 × ₹120 | C17: =C16*'Core Inputs'!B6 -> 7200 | D17: ₹ | E17: Savings created
A18: Elite bonus | B18: 25% × savings | C18: =25%*C17 -> 1800 | D18: ₹ | E18: Bonus linked to avoided RTO savings
A19: Bonus / delivery | B19: Bonus ÷ 2,000 | C19: =C18/2000 -> 0.9 | D19: ₹ / delivery | E19: Illustrative payout intensity
A20: Coverage condition | B20: Partner must meet scorecard rules | D20: Qualitative | E20: Bonus only within defined governance framework
A22: Governance guardrails that protect the economics
A23: Guardrail | B23: Why it is needed | C23: Mechanism
A24: Difficulty adjustment | B24: Do not penalise hard rural mixes | C24: Actual performance vs expected for order mix
A25: Attribution | B25: Exclude failures outside partner control | C25: Customer / seller / network / weather / allocation excluded
A26: Verified attempt | B26: Prevent fake NDR or fake effort | C26: GPS + call + dwell + customer confirmation
A27: Hard gates | B27: Separate severe misconduct from score | C27: COD misappropriation, theft/tampering, fabricated POD, serious DNRS, fake attempts, false documents
A28: Operating rule | B28: Avoid one bad week causing demotion | C28: Rolling 4 weeks, updated weekly, min 150 orders, 2 consecutive weeks to demote

Sheet Portfolio Scenario
A1: PORTFOLIO SCENARIO | LINK THE SOLUTIONS TO THE RTO POOL
A2: Illustrative monthly scenario based on the recoverable RTO pool identified on the problem-sizing slide.
A4: Core inputs | F4: Calculated outcome
A5: Input | B5: Value | C5: Unit | D5: Basis | F5: Metric | G5: Formula | H5: Result
A6: Orders / month | B6: 1000000 | C6: orders | D6: Illustrative slide scenario | F6: RTO reduction | H6: =B8*B9 -> 0.02735
A7: Current blended RTO | B7: 0.17 | C7: % | D7: DICE case-pack | F7: Post-intervention RTO | H7: =B7-H6 -> 0.14265
A8: Recoverable RTO pool | B8: 0.0547 | C8: % | D8: 5.47pp from six actionable problems | F8: RTOs avoided / month | H8: =B6*H6 -> 27350
A9: Capture rate | B9: 0.5 | C9: % | D9: Illustrative year-1 scenario | F9: Reverse cost savings / month | H9: =H8*B10 -> 3282000
A10: Incremental reverse cost | B10: ='Core Inputs'!B6 -> 120 | C10: ₹ / RTO | D10: Case-pack | F10: Savings / year | H10: =H9*12 -> 39384000
F11: Cost per successful delivery after reduction | H11: ='Core Inputs'!B5/(1-H7) -> 58.31924
A13: What this means for Slide 9
A14: Layer | B14: Unit economics logic | C14: Pilot proof point | D14: Scale gate
A15: Solution 1: Customer-rider coordination | B15: Pre-dispatch: P(save) × ₹170 − cost | C15: Incremental NDR→delivery uplift | D15: Cost / saved order vs ₹170
A16: Solution 2: Rider economics | B16: Premium capped by P(save) × ₹120 | C16: Verified difficult-delivery conversion | D16: Premium remains contribution-positive
A17: Solution 3: Rural Connection Shield | B17: Avoided delay / RTO value vs protection cost | C17: P90/P95 tail + connection miss rate | D17: Cost / hour saved + RTO impact
A18: Solution 4 + 8: Partner + Flash Store | B18: Execution quality and local recovery create / protect value | C18: Partner score + recovery net value | D18: Economics + CX + SLA + risk all hold
